e3response/__init__.py
e3response/_logging.py
e3response/cli.py
e3response/config.py
e3response/electric.py
e3response/eval.py
e3response/keys.py
e3response/losses.py
e3response/train.py
e3response/data/__init__.py
e3response/data/barium_titanate.py
e3response/data/components/__init__.py
e3response/utils/__init__.py
e3response/utils/instantiators.py
e3response/utils/logging_utils.py
e3response/utils/pylogger.py
e3response/utils/rich_utils.py
e3response/utils/utils.py
e3response-0.1.2.data/data/eval.yaml
e3response-0.1.2.data/data/train.yaml
e3response-0.1.2.data/data/data/bto.yaml
e3response-0.1.2.data/data/extras/default.yaml
e3response-0.1.2.data/data/hydra/default.yaml
e3response-0.1.2.data/data/listeners/default.yaml
e3response-0.1.2.data/data/listeners/early_stopping.yaml
e3response-0.1.2.data/data/listeners/model_checkpoint.yaml
e3response-0.1.2.data/data/listeners/model_summary.yaml
e3response-0.1.2.data/data/listeners/none.yaml
e3response-0.1.2.data/data/listeners/rich_progress_bar.yaml
e3response-0.1.2.data/data/logger/csv.yaml
e3response-0.1.2.data/data/logger/many_loggers.yaml
e3response-0.1.2.data/data/logger/mlflow.yaml
e3response-0.1.2.data/data/logger/tensorboard.yaml
e3response-0.1.2.data/data/model/mace.yaml
e3response-0.1.2.data/data/model/nequip.yaml
e3response-0.1.2.data/data/model/nequip_deriv.yaml
e3response-0.1.2.data/data/model/nequip_nmr.yaml
e3response-0.1.2.data/data/paths/default.yaml
e3response-0.1.2.data/data/trainer/cpu.yaml
e3response-0.1.2.data/data/trainer/ddp.yaml
e3response-0.1.2.data/data/trainer/ddp_sim.yaml
e3response-0.1.2.data/data/trainer/default.yaml
e3response-0.1.2.data/data/trainer/gpu.yaml
e3response-0.1.2.data/data/trainer/mps.yaml
e3response-0.1.2.dist-info/entry_points.txt
e3response-0.1.2.dist-info/licenses/LICENSE.txt
e3response-0.1.2.dist-info/WHEEL
e3response-0.1.2.dist-info/METADATA
e3response-0.1.2.dist-info/RECORD
